{
    "alt-version(s)": [
        "Single Strike Style",
        "Rapid Strike Style"
    ],
    "Single Strike Style": {
        "pokedex_data": {
            "National No.": "0892",
            "Type": [
                "Fighting",
                "Dark"
            ],
            "Species": "Wushu Poke\u0301mon",
            "Height": "1.9 m (6\u203203\u2032\u2032)",
            "Weight": "105.0 kg (231.5 lbs)",
            "Abilities": {
                "Unseen Fist": {
                    "href": "/ability/unseen-fist",
                    "effect": "Contact moves can strike through Protect/Detect.",
                    "hidden": false
                }
            }
        },
        "training_data": {
            "EV yield": "3 Attack",
            "Catch rate": "3",
            "BaseFriendship": "50",
            "Base Exp.": "275",
            "Growth Rate": "Slow"
        },
        "breeding_data": {
            "Gender": "87.5% male,12.5% female"
        },
        "base_stats": {
            "HP": {
                "Base": "100",
                "Min": "310",
                "Max": "404"
            },
            "Attack": {
                "Base": "130",
                "Min": "238",
                "Max": "394"
            },
            "Defense": {
                "Base": "100",
                "Min": "184",
                "Max": "328"
            },
            "Sp. Atk": {
                "Base": "63",
                "Min": "117",
                "Max": "247"
            },
            "Sp. Def": {
                "Base": "60",
                "Min": "112",
                "Max": "240"
            },
            "Speed": {
                "Base": "97",
                "Min": "179",
                "Max": "322"
            },
            "Total": "550"
        },
        "defense_stats": {
            "default": {
                "Fighting": "super-effective",
                "Flying": "super-effective",
                "Psychic": "no effect",
                "Rock": "not very effective",
                "Ghost": "not very effective",
                "Dark": "not very effective",
                "Fairy": "super-effective"
            }
        }
    },
    "Rapid Strike Style": {
        "pokedex_data": {
            "National No.": "0892",
            "Type": [
                "Fighting",
                "Water"
            ],
            "Species": "Wushu Poke\u0301mon",
            "Height": "1.9 m (6\u203203\u2032\u2032)",
            "Weight": "105.0 kg (231.5 lbs)",
            "Abilities": {
                "Unseen Fist": {
                    "href": "/ability/unseen-fist",
                    "effect": "Contact moves can strike through Protect/Detect.",
                    "hidden": false
                }
            }
        },
        "training_data": {
            "EV yield": "3 Attack",
            "Catch rate": "3",
            "BaseFriendship": "50",
            "Base Exp.": "275",
            "Growth Rate": "Slow"
        },
        "breeding_data": {
            "Gender": "87.5% male,12.5% female"
        },
        "base_stats": {
            "HP": {
                "Base": "100",
                "Min": "310",
                "Max": "404"
            },
            "Attack": {
                "Base": "130",
                "Min": "238",
                "Max": "394"
            },
            "Defense": {
                "Base": "100",
                "Min": "184",
                "Max": "328"
            },
            "Sp. Atk": {
                "Base": "63",
                "Min": "117",
                "Max": "247"
            },
            "Sp. Def": {
                "Base": "60",
                "Min": "112",
                "Max": "240"
            },
            "Speed": {
                "Base": "97",
                "Min": "179",
                "Max": "322"
            },
            "Total": "550"
        },
        "defense_stats": {
            "default": {
                "Fire": "not very effective",
                "Water": "not very effective",
                "Electric": "super-effective",
                "Grass": "super-effective",
                "Ice": "not very effective",
                "Flying": "super-effective",
                "Psychic": "super-effective",
                "Bug": "not very effective",
                "Rock": "not very effective",
                "Dark": "not very effective",
                "Steel": "not very effective",
                "Fairy": "super-effective"
            }
        }
    },
    "evo_stats": [
        [
            {
                "from": {
                    "name": "Kubfu",
                    "nationalNo": "#0891",
                    "type": [
                        "Fighting"
                    ],
                    "nickname": null
                },
                "to": {
                    "name": "Urshifu",
                    "nationalNo": "#0892",
                    "type": [
                        "Fighting",
                        "Dark"
                    ],
                    "nickname": "Single Strike Style"
                },
                "requirement": "(use Scroll Of Darkness, or in Tower of Darkness in Galar)",
                "shed": null
            },
            {
                "from": {
                    "name": "Kubfu",
                    "nationalNo": "#0891",
                    "type": [
                        "Fighting"
                    ],
                    "nickname": null
                },
                "to": {
                    "name": "Urshifu",
                    "nationalNo": "#0892",
                    "type": [
                        "Fighting",
                        "Water"
                    ],
                    "nickname": "Rapid Strike Style"
                },
                "requirement": "(use Scroll Of Waters, or in Tower of Water in Galar)",
                "shed": null
            }
        ]
    ],
    "attacks_data": {
        "Single Strike Style": {
            "moves": {
                "Endure": "1",
                "Focus Energy": "1",
                "Leer": "1",
                "Rock Smash": "1",
                "Sucker Punch": "1",
                "Aerial Ace": "12",
                "Scary Face": "16",
                "Headbutt": "20",
                "Brick Break": "24",
                "Detect": "28",
                "Bulk Up": "32",
                "Iron Head": "36",
                "Dynamic Punch": "40",
                "Counter": "44",
                "Close Combat": "48",
                "Focus Punch": "52"
            },
            "evolution": {
                "Wicked Blow": "75"
            },
            "tm": {
                "Take Down": "01",
                "Scary Face": "06",
                "Protect": "07",
                "Low Kick": "12",
                "Acrobatics": "14",
                "Trailblaze": "20",
                "Facade": "25",
                "Aerial Ace": "27",
                "Snarl": "30",
                "Metal Claw": "31",
                "Swift": "32",
                "Rock Tomb": "36",
                "Low Sweep": "39",
                "Fling": "43",
                "Endure": "47",
                "Dig": "55",
                "False Swipe": "57",
                "Brick Break": "58",
                "Zen Headbutt": "59",
                "U-turn": "60",
                "Foul Play": "62",
                "Bulk Up": "64",
                "Body Slam": "66",
                "Fire Punch": "67",
                "Thunder Punch": "68",
                "Ice Punch": "69",
                "Sleep Talk": "70",
                "Drain Punch": "73",
                "Poison Jab": "83",
                "Rest": "85",
                "Rock Slide": "86",
                "Taunt": "87",
                "Swords Dance": "88",
                "Body Press": "89",
                "Dark Pulse": "94",
                "Iron Head": "99",
                "Substitute": "103",
                "Iron Defense": "104",
                "Crunch": "108",
                "Aura Sphere": "112",
                "Helping Hand": "130",
                "Reversal": "134",
                "Stone Edge": "150",
                "Giga Impact": "152",
                "Focus Blast": "158",
                "Close Combat": "167",
                "Tera Blast": "171"
            }
        },
        "Rapid Strike Style": {
            "moves": {
                "Aqua Jet": "1",
                "Endure": "1",
                "Focus Energy": "1",
                "Leer": "1",
                "Rock Smash": "1",
                "Aerial Ace": "12",
                "Scary Face": "16",
                "Headbutt": "20",
                "Brick Break": "24",
                "Detect": "28",
                "Bulk Up": "32",
                "Iron Head": "36",
                "Dynamic Punch": "40",
                "Counter": "44",
                "Close Combat": "48",
                "Focus Punch": "52"
            },
            "evolution": {
                "Surging Strikes": "25"
            },
            "tm": {
                "Take Down": "01",
                "Scary Face": "06",
                "Protect": "07",
                "Low Kick": "12",
                "Acrobatics": "14",
                "Trailblaze": "20",
                "Chilling Water": "22",
                "Facade": "25",
                "Aerial Ace": "27",
                "Swift": "32",
                "Rock Tomb": "36",
                "Low Sweep": "39",
                "Fling": "43",
                "Endure": "47",
                "Rain Dance": "50",
                "Dig": "55",
                "False Swipe": "57",
                "Brick Break": "58",
                "Zen Headbutt": "59",
                "U-turn": "60",
                "Bulk Up": "64",
                "Body Slam": "66",
                "Fire Punch": "67",
                "Thunder Punch": "68",
                "Ice Punch": "69",
                "Sleep Talk": "70",
                "Drain Punch": "73",
                "Waterfall": "77",
                "Poison Jab": "83",
                "Rest": "85",
                "Rock Slide": "86",
                "Taunt": "87",
                "Swords Dance": "88",
                "Body Press": "89",
                "Iron Head": "99",
                "Substitute": "103",
                "Iron Defense": "104",
                "Liquidation": "110",
                "Aura Sphere": "112",
                "Ice Spinner": "124",
                "Helping Hand": "130",
                "Reversal": "134",
                "Stone Edge": "150",
                "Giga Impact": "152",
                "Focus Blast": "158",
                "Close Combat": "167",
                "Tera Blast": "171"
            }
        },
        "egg": null
    },
    "entries": {
        "Gigantamax Single Strike Style": [
            "People call it the embodiment of rage. It\u2019s said that this Pok\u00e9mon\u2019s terrifying expression and shout will rid the world of malevolence.",
            "The energy released by this Pok\u00e9mon\u2019s fists forms shock waves that can blow away Dynamax Pok\u00e9mon in just one hit."
        ],
        "Single Strike Style": [
            "This form of Urshifu is a strong believer in the one-hit KO. Its strategy is to leap in close to foes and land a devastating blow with a hardened fist.",
            "Inhabiting the mountains of a distant region, this Pok\u00e9mon races across sheer cliffs, training its legs and refining its moves."
        ],
        "Gigantamax Rapid Strike Style": [
            "As it waits for the right moment to unleash its Gigantamax power, this Pok\u00e9mon maintains a perfect one-legged stance. It won\u2019t even twitch.",
            "All it takes is a glare from this Pok\u00e9mon to take the lives of those with evil in their hearts\u2014or so they say."
        ],
        "Rapid Strike Style": [
            "It\u2019s believed that this Pok\u00e9mon modeled its fighting style on the flow of a river\u2014sometimes rapid, sometimes calm.",
            "This form of Urshifu is a strong believer in defeating foes by raining many blows down on them. Its strikes are nonstop, flowing like a river."
        ]
    },
    "name": "Urshifu"
}